Metadata-Version: 1.1
Name: pytabby
Version: 0.1.0
Summary: A simple, non-opinionated python terminal menu system WITH TABS
Home-page: http://github.com/Prooffreader/pytabby
Author: David Taylor
Author-email: prooffreader@gmail.com
License: MIT
Download-URL: https://github.com/Prooffreader/pytabby/archive/v0.1.0.tar.gz
Keywords: python,shell,terminal,console,tabs,tabbed,menu,menus
Platform: UNKNOWN
Classifier: Development Status :: 4 - Beta
Classifier: Intended Audience :: Developers
Classifier: License :: OSI Approved :: MIT License
Classifier: Operating System :: Unix
Classifier: Operating System :: POSIX
Classifier: Operating System :: Microsoft :: Windows
Classifier: Programming Language :: Python
Classifier: Programming Language :: Python :: 3
Classifier: Programming Language :: Python :: 3.6
Classifier: Programming Language :: Python :: 3.7
Classifier: Programming Language :: Python :: Implementation :: CPython
Classifier: Topic :: Software Development :: Libraries :: Python Modules
Classifier: Topic :: Utilities
